export_spdx/__init__.py
export_spdx/config.py
export_spdx/data.py
export_spdx/globals.py
export_spdx/main.py
export_spdx/process.py
export_spdx/projects.py
export_spdx/spdx.py
bd_export_spdx2.2-0.24.dist-info/LICENSE
bd_export_spdx2.2-0.24.dist-info/METADATA
bd_export_spdx2.2-0.24.dist-info/WHEEL
bd_export_spdx2.2-0.24.dist-info/entry_points.txt
bd_export_spdx2.2-0.24.dist-info/top_level.txt
bd_export_spdx2.2-0.24.dist-info/RECORD
