Metadata-Version: 2.1
Name: bd-export-spdx2.2
Version: 0.24
Summary: Export an SPDX version 2.2 JSON file from a Black Duck project.
Home-page: https://github.com/matthewb66/bd_export_spdx2.2
Author: Matthew Brady
Author-email: w3matt@gmail.com
License: UNKNOWN
Platform: UNKNOWN
Classifier: Programming Language :: Python :: 3
Classifier: License :: OSI Approved :: Apache Software License
Classifier: Operating System :: OS Independent
Requires-Python: >=3.0
License-File: LICENSE
Requires-Dist: blackduck (>=1.0.0)
Requires-Dist: lxml
Requires-Dist: aiohttp
